monitopy/__init__.py
monitopy/spectator.py
monitopy-0.0.3.dist-info/METADATA
monitopy-0.0.3.dist-info/WHEEL
monitopy-0.0.3.dist-info/top_level.txt
monitopy-0.0.3.dist-info/RECORD
